joker_xopen-0.1-py3.7-nspkg.pth
joker/xopen/__init__.py
joker/xopen/__main__.py
joker/xopen/client.py
joker/xopen/server.py
joker/xopen/utils.py
joker_xopen-0.1.dist-info/METADATA
joker_xopen-0.1.dist-info/WHEEL
joker_xopen-0.1.dist-info/entry_points.txt
joker_xopen-0.1.dist-info/namespace_packages.txt
joker_xopen-0.1.dist-info/top_level.txt
joker_xopen-0.1.dist-info/RECORD
