Metadata-Version: 2.1
Name: joker-xopen
Version: 0.1
Summary: Open files and URLs in desktop environments conveniently
Home-page: https://github.com/frozflame/joker-xopen
Author: frozflame
Author-email: frozflame@outlook.com
License: GNU General Public License (GPL)
Keywords: desktop open xdg-open start
Platform: UNKNOWN
Classifier: Programming Language :: Python
Classifier: Programming Language :: Python :: 3
Classifier: Programming Language :: Python :: 3.3
Classifier: Programming Language :: Python :: 3.4
Classifier: Programming Language :: Python :: 3.5
Classifier: Programming Language :: Python :: 3.6
Requires-Dist: volkanic
Requires-Dist: requests
Requires-Dist: joker
Requires-Dist: joker-cast
Requires-Dist: joker-minions
